{"1": [{"type": "move", "x": 16, "y": 6, "d": null, "p": null, "tau": 1182.7991520749968}, {"type": "load", "x": 6, "y": 6, "d": 8, "p": 0, "tau": 1202.7991520749968}, {"type": "move", "x": 6, "y": 4, "d": 8, "p": 1, "tau": 2270.8535958165676}, {"type": "unload", "x": 4, "y": 4, "d": 8, "p": 2, "tau": 2290.8535958165676}, {"type": "load", "x": 4, "y": 4, "d": 1, "p": 0, "tau": 2310.8535958165676}, {"type": "swap", "x": 4, "y": 4, "d": 1, "p": 1, "tau": 2370.8535958165676}, {"type": "move", "x": 4, "y": 8, "d": 1, "p": 2, "tau": 3776.1589972432457}, {"type": "unload", "x": 8, "y": 8, "d": 1, "p": 3, "tau": 3796.1589972432457}, {"type": "load", "x": 8, "y": 8, "d": 6, "p": 0, "tau": 3816.1589972432457}, {"type": "swap", "x": 8, "y": 8, "d": 6, "p": 1, "tau": 3876.1589972432457}, {"type": "move", "x": 8, "y": 5, "d": 6, "p": 2, "tau": 6224.326181844715}, {"type": "swap", "x": 5, "y": 5, "d": 6, "p": 3, "tau": 6284.326181844715}, {"type": "move", "x": 5, "y": 18, "d": 6, "p": 4, "tau": 8620.110567184547}, {"type": "unload", "x": 18, "y": 18, "d": 6, "p": 5, "tau": 8640.110567184547}], "2": [{"type": "move", "x": 18, "y": 9, "d": null, "p": null, "tau": 1611.4962367868231}, {"type": "load", "x": 9, "y": 9, "d": 4, "p": 0, "tau": 1631.4962367868231}, {"type": "swap", "x": 9, "y": 9, "d": 4, "p": 1, "tau": 1691.4962367868231}, {"type": "move", "x": 9, "y": 4, "d": 4, "p": 2, "tau": 3525.024925536966}, {"type": "unload", "x": 4, "y": 4, "d": 4, "p": 3, "tau": 3545.024925536966}, {"type": "swap", "x": 4, "y": 4, "d": null, "p": null, "tau": 3605.024925536966}, {"type": "move", "x": 4, "y": 6, "d": null, "p": null, "tau": 4673.079369278536}, {"type": "load", "x": 6, "y": 6, "d": 14, "p": 0, "tau": 4693.079369278536}, {"type": "move", "x": 6, "y": 4, "d": 14, "p": 1, "tau": 5761.1338130201075}, {"type": "swap", "x": 4, "y": 4, "d": 14, "p": 2, "tau": 5821.1338130201075}, {"type": "move", "x": 4, "y": 3, "d": 14, "p": 3, "tau": 7497.73893809093}, {"type": "unload", "x": 3, "y": 3, "d": 14, "p": 4, "tau": 7517.73893809093}], "3": [{"type": "load", "x": 8, "y": 8, "d": 18, "p": 0, "tau": 20}, {"type": "move", "x": 8, "y": 11, "d": 18, "p": 1, "tau": 1566.907633982059}, {"type": "unload", "x": 11, "y": 11, "d": 18, "p": 2, "tau": 1586.907633982059}, {"type": "move", "x": 11, "y": 2, "d": null, "p": null, "tau": 2673.4713014688105}, {"type": "load", "x": 2, "y": 2, "d": 9, "p": 0, "tau": 2693.4713014688105}, {"type": "swap", "x": 2, "y": 2, "d": 9, "p": 1, "tau": 2753.4713014688105}, {"type": "move", "x": 2, "y": 9, "d": 9, "p": 2, "tau": 3973.365092225502}, {"type": "unload", "x": 9, "y": 9, "d": 9, "p": 3, "tau": 3993.365092225502}, {"type": "swap", "x": 9, "y": 9, "d": null, "p": null, "tau": 4053.365092225502}, {"type": "move", "x": 9, "y": 7, "d": null, "p": null, "tau": 5916.812732450892}, {"type": "load", "x": 7, "y": 7, "d": 20, "p": 0, "tau": 5936.812732450892}, {"type": "move", "x": 7, "y": 15, "d": 20, "p": 1, "tau": 6852.386399351838}, {"type": "swap", "x": 15, "y": 15, "d": 20, "p": 2, "tau": 6912.386399351838}, {"type": "move", "x": 15, "y": 10, "d": 20, "p": 3, "tau": 8198.334977241482}, {"type": "swap", "x": 10, "y": 10, "d": 20, "p": 4, "tau": 8258.334977241482}, {"type": "move", "x": 10, "y": 18, "d": 20, "p": 5, "tau": 9083.701237402252}, {"type": "unload", "x": 18, "y": 18, "d": 20, "p": 6, "tau": 9103.701237402252}], "4": [{"type": "move", "x": 16, "y": 7, "d": null, "p": null, "tau": 1022.0148403654035}, {"type": "load", "x": 7, "y": 7, "d": 7, "p": 0, "tau": 1042.0148403654034}, {"type": "move", "x": 7, "y": 19, "d": 7, "p": 1, "tau": 2817.610403662525}, {"type": "unload", "x": 19, "y": 19, "d": 7, "p": 2, "tau": 2837.610403662525}, {"type": "load", "x": 19, "y": 19, "d": 19, "p": 0, "tau": 2857.610403662525}, {"type": "swap", "x": 19, "y": 19, "d": 19, "p": 1, "tau": 2917.610403662525}, {"type": "move", "x": 19, "y": 13, "d": 19, "p": 2, "tau": 4830.343261747744}, {"type": "unload", "x": 13, "y": 13, "d": 19, "p": 3, "tau": 4850.343261747744}, {"type": "swap", "x": 13, "y": 13, "d": null, "p": null, "tau": 4910.343261747744}, {"type": "move", "x": 13, "y": 7, "d": null, "p": null, "tau": 6859.83355648412}, {"type": "load", "x": 7, "y": 7, "d": 16, "p": 3, "tau": 6879.83355648412}, {"type": "move", "x": 7, "y": 15, "d": 16, "p": 4, "tau": 7795.407223385066}, {"type": "swap", "x": 15, "y": 15, "d": 16, "p": 5, "tau": 7855.407223385066}, {"type": "move", "x": 15, "y": 13, "d": 16, "p": 6, "tau": 8905.766684181688}, {"type": "unload", "x": 13, "y": 13, "d": 16, "p": 7, "tau": 8925.766684181688}], "5": [{"type": "move", "x": 8, "y": 12, "d": null, "p": null, "tau": 742.6092586126606}, {"type": "load", "x": 12, "y": 12, "d": 15, "p": 0, "tau": 762.6092586126606}, {"type": "move", "x": 12, "y": 6, "d": 15, "p": 1, "tau": 1738.9838336258308}, {"type": "unload", "x": 6, "y": 6, "d": 15, "p": 2, "tau": 1758.9838336258308}, {"type": "load", "x": 6, "y": 6, "d": 13, "p": 0, "tau": 1778.9838336258308}, {"type": "move", "x": 6, "y": 16, "d": 13, "p": 1, "tau": 2961.7829857008273}, {"type": "swap", "x": 16, "y": 16, "d": 13, "p": 2, "tau": 3021.7829857008273}, {"type": "move", "x": 16, "y": 19, "d": 13, "p": 3, "tau": 4298.925820098141}, {"type": "unload", "x": 19, "y": 19, "d": 13, "p": 4, "tau": 4318.925820098141}, {"type": "load", "x": 19, "y": 19, "d": 17, "p": 0, "tau": 4338.925820098141}, {"type": "swap", "x": 19, "y": 19, "d": 17, "p": 1, "tau": 4398.925820098141}, {"type": "move", "x": 19, "y": 14, "d": 17, "p": 2, "tau": 5156.403234194675}, {"type": "unload", "x": 14, "y": 14, "d": 17, "p": 3, "tau": 5176.403234194675}, {"type": "move", "x": 14, "y": 9, "d": null, "p": null, "tau": 7414.674909371652}, {"type": "load", "x": 9, "y": 9, "d": 9, "p": 4, "tau": 7434.674909371652}, {"type": "swap", "x": 9, "y": 9, "d": 9, "p": 5, "tau": 7494.674909371652}, {"type": "move", "x": 9, "y": 10, "d": 9, "p": 6, "tau": 8398.479021034827}, {"type": "swap", "x": 10, "y": 10, "d": 9, "p": 7, "tau": 8458.479021034827}, {"type": "move", "x": 10, "y": 18, "d": 9, "p": 8, "tau": 9283.845281195598}, {"type": "unload", "x": 18, "y": 18, "d": 9, "p": 9, "tau": 9303.845281195598}], "6": [{"type": "move", "x": 18, "y": 17, "d": null, "p": null, "tau": 1972.865824733486}, {"type": "load", "x": 17, "y": 17, "d": 12, "p": 0, "tau": 1992.865824733486}, {"type": "move", "x": 17, "y": 15, "d": 12, "p": 1, "tau": 2901.1098435329095}, {"type": "swap", "x": 15, "y": 15, "d": 12, "p": 2, "tau": 2961.1098435329095}, {"type": "move", "x": 15, "y": 5, "d": 12, "p": 3, "tau": 3908.614486357232}, {"type": "swap", "x": 5, "y": 5, "d": 12, "p": 4, "tau": 3968.614486357232}, {"type": "move", "x": 5, "y": 2, "d": 12, "p": 5, "tau": 4759.718398725787}, {"type": "swap", "x": 2, "y": 2, "d": 12, "p": 6, "tau": 4819.718398725787}, {"type": "move", "x": 2, "y": 1, "d": 12, "p": 7, "tau": 5614.106447563016}, {"type": "unload", "x": 1, "y": 1, "d": 12, "p": 8, "tau": 5634.106447563016}, {"type": "load", "x": 1, "y": 1, "d": 3, "p": 0, "tau": 5654.106447563016}, {"type": "swap", "x": 1, "y": 1, "d": 3, "p": 1, "tau": 5714.106447563016}, {"type": "move", "x": 1, "y": 2, "d": 3, "p": 2, "tau": 6508.494496400246}, {"type": "swap", "x": 2, "y": 2, "d": 3, "p": 3, "tau": 6568.494496400246}, {"type": "move", "x": 2, "y": 5, "d": 3, "p": 4, "tau": 7359.598408768801}, {"type": "swap", "x": 5, "y": 5, "d": 3, "p": 5, "tau": 7419.598408768801}, {"type": "move", "x": 5, "y": 15, "d": 3, "p": 6, "tau": 8367.103051593123}, {"type": "swap", "x": 15, "y": 15, "d": 3, "p": 7, "tau": 8427.103051593123}, {"type": "move", "x": 15, "y": 14, "d": 3, "p": 8, "tau": 9388.096429919959}, {"type": "unload", "x": 14, "y": 14, "d": 3, "p": 9, "tau": 9408.096429919959}], "7": [{"type": "move", "x": 11, "y": 1, "d": null, "p": null, "tau": 1329.2713556486613}, {"type": "load", "x": 1, "y": 1, "d": 5, "p": 0, "tau": 1349.2713556486613}, {"type": "move", "x": 1, "y": 3, "d": 5, "p": 1, "tau": 2100.4151089650704}, {"type": "unload", "x": 3, "y": 3, "d": 5, "p": 2, "tau": 2120.4151089650704}, {"type": "load", "x": 3, "y": 3, "d": 11, "p": 0, "tau": 2140.4151089650704}, {"type": "swap", "x": 3, "y": 3, "d": 11, "p": 1, "tau": 2200.4151089650704}, {"type": "move", "x": 3, "y": 5, "d": 11, "p": 2, "tau": 3328.375767766802}, {"type": "swap", "x": 5, "y": 5, "d": 11, "p": 3, "tau": 3388.375767766802}, {"type": "move", "x": 5, "y": 15, "d": 11, "p": 4, "tau": 4335.880410591125}, {"type": "swap", "x": 15, "y": 15, "d": 11, "p": 5, "tau": 4395.880410591125}, {"type": "move", "x": 15, "y": 14, "d": 11, "p": 6, "tau": 5356.873788917961}, {"type": "unload", "x": 14, "y": 14, "d": 11, "p": 7, "tau": 5376.873788917961}, {"type": "load", "x": 14, "y": 14, "d": 17, "p": 4, "tau": 5396.873788917961}, {"type": "swap", "x": 14, "y": 14, "d": 17, "p": 5, "tau": 5456.873788917961}, {"type": "move", "x": 14, "y": 15, "d": 17, "p": 6, "tau": 6417.867167244797}, {"type": "swap", "x": 15, "y": 15, "d": 17, "p": 7, "tau": 6477.867167244797}, {"type": "move", "x": 15, "y": 5, "d": 17, "p": 8, "tau": 7425.37181006912}, {"type": "swap", "x": 5, "y": 5, "d": 17, "p": 9, "tau": 7485.37181006912}, {"type": "move", "x": 5, "y": 2, "d": 17, "p": 10, "tau": 8276.475722437675}, {"type": "swap", "x": 2, "y": 2, "d": 17, "p": 11, "tau": 8336.475722437675}, {"type": "move", "x": 2, "y": 3, "d": 17, "p": 12, "tau": 9080.26112986194}, {"type": "unload", "x": 3, "y": 3, "d": 17, "p": 13, "tau": 9100.26112986194}], "8": [{"type": "move", "x": 17, "y": 15, "d": null, "p": null, "tau": 908.2440187994234}, {"type": "load", "x": 15, "y": 15, "d": 10, "p": 0, "tau": 928.2440187994234}, {"type": "move", "x": 15, "y": 16, "d": 10, "p": 1, "tau": 2554.7376366581993}, {"type": "unload", "x": 16, "y": 16, "d": 10, "p": 2, "tau": 2574.7376366581993}, {"type": "move", "x": 16, "y": 6, "d": null, "p": null, "tau": 3757.536788733196}, {"type": "load", "x": 6, "y": 6, "d": 16, "p": 0, "tau": 3777.536788733196}, {"type": "move", "x": 6, "y": 7, "d": 16, "p": 1, "tau": 4751.672766171289}, {"type": "unload", "x": 7, "y": 7, "d": 16, "p": 2, "tau": 4771.672766171289}, {"type": "load", "x": 7, "y": 7, "d": 2, "p": 0, "tau": 4791.672766171289}, {"type": "swap", "x": 7, "y": 7, "d": 2, "p": 1, "tau": 4851.672766171289}, {"type": "move", "x": 7, "y": 15, "d": 2, "p": 2, "tau": 5767.246433072235}, {"type": "swap", "x": 15, "y": 15, "d": 2, "p": 3, "tau": 5827.246433072235}, {"type": "move", "x": 15, "y": 13, "d": 2, "p": 4, "tau": 6877.6058938688575}, {"type": "swap", "x": 13, "y": 13, "d": 2, "p": 5, "tau": 6937.6058938688575}, {"type": "move", "x": 13, "y": 10, "d": 2, "p": 6, "tau": 7728.428498561199}, {"type": "swap", "x": 10, "y": 10, "d": 2, "p": 7, "tau": 7788.428498561199}, {"type": "move", "x": 10, "y": 18, "d": 2, "p": 8, "tau": 8613.79475872197}, {"type": "unload", "x": 18, "y": 18, "d": 2, "p": 9, "tau": 8633.79475872197}]}