{"1": [{"type": "load", "x": 12, "y": 12, "d": 5, "p": 0, "tau": 20}, {"type": "move", "x": 12, "y": 13, "d": 5, "p": 1, "tau": 1004.2638875209472}, {"type": "swap", "x": 13, "y": 13, "d": 5, "p": 2, "tau": 1064.2638875209473}, {"type": "move", "x": 13, "y": 17, "d": 5, "p": 3, "tau": 1965.2239362062878}, {"type": "unload", "x": 17, "y": 17, "d": 5, "p": 4, "tau": 1985.2239362062878}], "2": [{"type": "move", "x": 20, "y": 12, "d": null, "p": null, "tau": 756.6255088788405}, {"type": "load", "x": 12, "y": 12, "d": 7, "p": 0, "tau": 776.6255088788405}, {"type": "move", "x": 12, "y": 11, "d": 7, "p": 1, "tau": 3206.8483793204696}, {"type": "unload", "x": 11, "y": 11, "d": 7, "p": 2, "tau": 3226.8483793204696}], "3": [], "4": [{"type": "move", "x": 1, "y": 19, "d": null, "p": null, "tau": 1722.4908633782031}, {"type": "load", "x": 19, "y": 19, "d": 13, "p": 0, "tau": 1742.4908633782031}, {"type": "move", "x": 19, "y": 14, "d": 13, "p": 1, "tau": 2917.057345965831}, {"type": "unload", "x": 14, "y": 14, "d": 13, "p": 2, "tau": 2937.057345965831}], "5": [{"type": "move", "x": 15, "y": 4, "d": null, "p": null, "tau": 887.4594558339777}, {"type": "load", "x": 4, "y": 4, "d": 2, "p": 0, "tau": 907.4594558339777}, {"type": "swap", "x": 4, "y": 4, "d": 2, "p": 1, "tau": 967.4594558339777}, {"type": "move", "x": 4, "y": 6, "d": 2, "p": 2, "tau": 2167.5753130876997}, {"type": "swap", "x": 6, "y": 6, "d": 2, "p": 3, "tau": 2227.5753130876997}, {"type": "move", "x": 6, "y": 19, "d": 2, "p": 4, "tau": 2951.46556591595}, {"type": "unload", "x": 19, "y": 19, "d": 2, "p": 5, "tau": 2971.46556591595}], "6": [], "7": [{"type": "load", "x": 4, "y": 4, "d": 12, "p": 0, "tau": 20}, {"type": "move", "x": 4, "y": 12, "d": 12, "p": 1, "tau": 1081.293819512195}, {"type": "unload", "x": 12, "y": 12, "d": 12, "p": 2, "tau": 1101.293819512195}], "8": [{"type": "move", "x": 6, "y": 19, "d": null, "p": null, "tau": 723.8902528282504}, {"type": "load", "x": 19, "y": 19, "d": 3, "p": 0, "tau": 743.8902528282504}, {"type": "move", "x": 19, "y": 20, "d": 3, "p": 1, "tau": 3382.5969222120148}, {"type": "unload", "x": 20, "y": 20, "d": 3, "p": 2, "tau": 3402.5969222120148}], "9": [{"type": "load", "x": 10, "y": 10, "d": 11, "p": 0, "tau": 20}, {"type": "move", "x": 10, "y": 6, "d": 11, "p": 1, "tau": 2245.1627416318524}, {"type": "unload", "x": 6, "y": 6, "d": 11, "p": 2, "tau": 2265.1627416318524}], "10": [{"type": "load", "x": 11, "y": 11, "d": 10, "p": 0, "tau": 20}, {"type": "move", "x": 11, "y": 15, "d": 10, "p": 1, "tau": 975.6884653219657}, {"type": "swap", "x": 15, "y": 15, "d": 10, "p": 2, "tau": 1035.6884653219659}, {"type": "move", "x": 15, "y": 4, "d": 10, "p": 3, "tau": 1923.1479211559435}, {"type": "unload", "x": 4, "y": 4, "d": 10, "p": 4, "tau": 1943.1479211559435}], "11": [{"type": "load", "x": 17, "y": 17, "d": 9, "p": 0, "tau": 20}, {"type": "move", "x": 17, "y": 10, "d": 9, "p": 1, "tau": 1352.0947283331896}, {"type": "unload", "x": 10, "y": 10, "d": 9, "p": 2, "tau": 1372.0947283331896}], "12": [], "13": [{"type": "load", "x": 7, "y": 7, "d": 6, "p": 0, "tau": 20}, {"type": "move", "x": 7, "y": 14, "d": 6, "p": 1, "tau": 1786.6840074286306}, {"type": "swap", "x": 14, "y": 14, "d": 6, "p": 2, "tau": 1846.6840074286306}, {"type": "move", "x": 14, "y": 12, "d": 6, "p": 3, "tau": 2774.4812105668634}, {"type": "unload", "x": 12, "y": 12, "d": 6, "p": 4, "tau": 2794.4812105668634}], "14": [{"type": "move", "x": 19, "y": 7, "d": null, "p": null, "tau": 721.990480536596}, {"type": "load", "x": 7, "y": 7, "d": 1, "p": 0, "tau": 741.990480536596}, {"type": "move", "x": 7, "y": 3, "d": 1, "p": 1, "tau": 1675.573679910509}, {"type": "swap", "x": 3, "y": 3, "d": 1, "p": 2, "tau": 1735.573679910509}, {"type": "move", "x": 3, "y": 1, "d": 1, "p": 3, "tau": 2476.9274669110628}, {"type": "swap", "x": 1, "y": 1, "d": 1, "p": 4, "tau": 2536.9274669110628}, {"type": "move", "x": 1, "y": 8, "d": 1, "p": 5, "tau": 3595.0518136896108}, {"type": "unload", "x": 8, "y": 8, "d": 1, "p": 6, "tau": 3615.0518136896108}], "15": [{"type": "move", "x": 16, "y": 8, "d": null, "p": null, "tau": 842.6223618887798}, {"type": "load", "x": 8, "y": 8, "d": 14, "p": 0, "tau": 862.6223618887798}, {"type": "move", "x": 8, "y": 6, "d": 14, "p": 1, "tau": 2938.8783296767656}, {"type": "unload", "x": 6, "y": 6, "d": 14, "p": 2, "tau": 2958.8783296767656}], "16": [], "17": [{"type": "move", "x": 13, "y": 17, "d": null, "p": null, "tau": 900.9600486853407}, {"type": "load", "x": 17, "y": 17, "d": 4, "p": 0, "tau": 920.9600486853407}, {"type": "move", "x": 17, "y": 10, "d": 4, "p": 1, "tau": 2253.0547770185303}, {"type": "unload", "x": 10, "y": 10, "d": 4, "p": 2, "tau": 2273.0547770185303}], "18": [{"type": "load", "x": 1, "y": 1, "d": 8, "p": 3, "tau": 1639.0124613481253}, {"type": "move", "x": 1, "y": 2, "d": 8, "p": 4, "tau": 2386.5018953115127}, {"type": "unload", "x": 2, "y": 2, "d": 8, "p": 5, "tau": 2406.5018953115127}], "19": [{"type": "load", "x": 17, "y": 17, "d": 15, "p": 0, "tau": 20}, {"type": "move", "x": 17, "y": 15, "d": 15, "p": 1, "tau": 833.9808590067978}, {"type": "swap", "x": 15, "y": 15, "d": 15, "p": 2, "tau": 893.9808590067978}, {"type": "move", "x": 15, "y": 2, "d": 15, "p": 3, "tau": 2070.8930869219794}, {"type": "swap", "x": 2, "y": 2, "d": 15, "p": 4, "tau": 2130.8930869219794}, {"type": "move", "x": 2, "y": 5, "d": 15, "p": 5, "tau": 3460.5631279877107}, {"type": "unload", "x": 5, "y": 5, "d": 15, "p": 6, "tau": 3480.5631279877107}], "20": [{"type": "load", "x": 7, "y": 7, "d": 8, "p": 0, "tau": 20}, {"type": "move", "x": 7, "y": 1, "d": 8, "p": 1, "tau": 1599.0124613481253}, {"type": "unload", "x": 1, "y": 1, "d": 8, "p": 2, "tau": 1619.0124613481253}], "21": [{"type": "move", "x": 14, "y": 2, "d": null, "p": null, "tau": 1707.201383144447}, {"type": "load", "x": 2, "y": 2, "d": 8, "p": 6, "tau": 2426.5018953115127}, {"type": "move", "x": 2, "y": 11, "d": 8, "p": 7, "tau": 3994.012207479779}, {"type": "unload", "x": 11, "y": 11, "d": 8, "p": 8, "tau": 4014.012207479779}], "22": [{"type": "move", "x": 13, "y": 10, "d": null, "p": null, "tau": 1604.6119029438767}, {"type": "load", "x": 10, "y": 10, "d": 9, "p": 3, "tau": 1624.6119029438767}, {"type": "move", "x": 10, "y": 9, "d": 9, "p": 4, "tau": 3489.0719107883547}, {"type": "unload", "x": 9, "y": 9, "d": 9, "p": 5, "tau": 3509.0719107883547}]}