{"1": [{"type": "load", "x": 13, "y": 13, "d": 23, "p": 0, "tau": 20}, {"type": "move", "x": 13, "y": 10, "d": 23, "p": 1, "tau": 2265.3615779627958}, {"type": "unload", "x": 10, "y": 10, "d": 23, "p": 2, "tau": 2285.3615779627958}, {"type": "load", "x": 10, "y": 10, "d": 16, "p": 0, "tau": 2305.3615779627958}, {"type": "move", "x": 10, "y": 5, "d": 16, "p": 1, "tau": 3182.223622894959}, {"type": "swap", "x": 5, "y": 5, "d": 16, "p": 2, "tau": 3242.223622894959}, {"type": "move", "x": 5, "y": 7, "d": 16, "p": 3, "tau": 4075.490764912781}, {"type": "swap", "x": 7, "y": 7, "d": 16, "p": 4, "tau": 4135.490764912781}, {"type": "move", "x": 7, "y": 11, "d": 16, "p": 5, "tau": 5005.145690525367}, {"type": "swap", "x": 11, "y": 11, "d": 16, "p": 6, "tau": 5065.145690525367}, {"type": "move", "x": 11, "y": 2, "d": 16, "p": 7, "tau": 5993.313670420699}, {"type": "unload", "x": 2, "y": 2, "d": 16, "p": 8, "tau": 6013.313670420699}], "2": [{"type": "load", "x": 4, "y": 4, "d": 10, "p": 0, "tau": 20}, {"type": "move", "x": 4, "y": 15, "d": 10, "p": 1, "tau": 1647.0943471946696}, {"type": "unload", "x": 15, "y": 15, "d": 10, "p": 2, "tau": 1667.0943471946696}, {"type": "move", "x": 15, "y": 10, "d": null, "p": null, "tau": 2639.101431331046}, {"type": "load", "x": 10, "y": 10, "d": 2, "p": 0, "tau": 2659.101431331046}, {"type": "swap", "x": 10, "y": 10, "d": 2, "p": 1, "tau": 2719.101431331046}, {"type": "move", "x": 10, "y": 2, "d": 2, "p": 2, "tau": 5633.612834742895}, {"type": "unload", "x": 2, "y": 2, "d": 2, "p": 3, "tau": 5653.612834742895}], "3": [{"type": "move", "x": 16, "y": 6, "d": null, "p": null, "tau": 1104.1980705582762}, {"type": "load", "x": 6, "y": 6, "d": 5, "p": 0, "tau": 1124.1980705582762}, {"type": "move", "x": 6, "y": 15, "d": 5, "p": 1, "tau": 1888.3718924779757}, {"type": "unload", "x": 15, "y": 15, "d": 5, "p": 2, "tau": 1908.3718924779757}, {"type": "move", "x": 15, "y": 5, "d": null, "p": null, "tau": 3347.9292635423635}, {"type": "load", "x": 5, "y": 5, "d": 15, "p": 0, "tau": 3367.9292635423635}, {"type": "swap", "x": 5, "y": 5, "d": 15, "p": 1, "tau": 3427.9292635423635}, {"type": "move", "x": 5, "y": 12, "d": 15, "p": 2, "tau": 5058.158142796262}, {"type": "swap", "x": 12, "y": 12, "d": 15, "p": 3, "tau": 5118.158142796262}, {"type": "move", "x": 12, "y": 18, "d": 15, "p": 4, "tau": 5963.359509854516}, {"type": "unload", "x": 18, "y": 18, "d": 15, "p": 5, "tau": 5983.359509854516}], "4": [{"type": "move", "x": 9, "y": 19, "d": null, "p": null, "tau": 1622.1879258514234}, {"type": "load", "x": 19, "y": 19, "d": 7, "p": 0, "tau": 1642.1879258514234}, {"type": "move", "x": 19, "y": 15, "d": 7, "p": 1, "tau": 2466.454110754067}, {"type": "unload", "x": 15, "y": 15, "d": 7, "p": 2, "tau": 2486.454110754067}, {"type": "move", "x": 15, "y": 20, "d": null, "p": null, "tau": 3331.8530498044684}, {"type": "swap", "x": 20, "y": 20, "d": null, "p": null, "tau": 3391.8530498044684}, {"type": "move", "x": 20, "y": 6, "d": null, "p": null, "tau": 4486.332843060453}, {"type": "load", "x": 6, "y": 6, "d": 11, "p": 4, "tau": 4506.332843060453}, {"type": "move", "x": 6, "y": 3, "d": 11, "p": 5, "tau": 6190.446255469635}, {"type": "unload", "x": 3, "y": 3, "d": 11, "p": 6, "tau": 6210.446255469635}], "5": [{"type": "load", "x": 17, "y": 17, "d": 18, "p": 0, "tau": 20}, {"type": "move", "x": 17, "y": 14, "d": 18, "p": 1, "tau": 940.9382445838088}, {"type": "unload", "x": 14, "y": 14, "d": 18, "p": 2, "tau": 960.9382445838088}, {"type": "load", "x": 14, "y": 14, "d": 21, "p": 0, "tau": 980.9382445838088}, {"type": "swap", "x": 14, "y": 14, "d": 21, "p": 1, "tau": 1040.9382445838087}, {"type": "move", "x": 14, "y": 7, "d": 21, "p": 2, "tau": 2940.525091565937}, {"type": "unload", "x": 7, "y": 7, "d": 21, "p": 3, "tau": 2960.525091565937}, {"type": "move", "x": 7, "y": 12, "d": null, "p": null, "tau": 3805.7927074548675}, {"type": "load", "x": 12, "y": 12, "d": 24, "p": 0, "tau": 3825.7927074548675}, {"type": "swap", "x": 12, "y": 12, "d": 24, "p": 1, "tau": 3885.7927074548675}, {"type": "move", "x": 12, "y": 11, "d": 24, "p": 2, "tau": 4904.004545711186}, {"type": "swap", "x": 11, "y": 11, "d": 24, "p": 3, "tau": 4964.004545711186}, {"type": "move", "x": 11, "y": 2, "d": 24, "p": 4, "tau": 5892.172525606518}, {"type": "unload", "x": 2, "y": 2, "d": 24, "p": 5, "tau": 5912.172525606518}], "6": [{"type": "move", "x": 9, "y": 10, "d": null, "p": null, "tau": 905.0329447969013}, {"type": "load", "x": 10, "y": 10, "d": 8, "p": 0, "tau": 925.0329447969013}, {"type": "move", "x": 10, "y": 14, "d": 8, "p": 1, "tau": 1793.7932467838568}, {"type": "unload", "x": 14, "y": 14, "d": 8, "p": 2, "tau": 1813.7932467838568}, {"type": "load", "x": 14, "y": 14, "d": 1, "p": 0, "tau": 1833.7932467838568}, {"type": "move", "x": 14, "y": 9, "d": 1, "p": 1, "tau": 2779.7306944211155}, {"type": "unload", "x": 9, "y": 9, "d": 1, "p": 2, "tau": 2799.7306944211155}, {"type": "load", "x": 9, "y": 9, "d": 17, "p": 0, "tau": 2819.7306944211155}, {"type": "swap", "x": 9, "y": 9, "d": 17, "p": 1, "tau": 2879.7306944211155}, {"type": "move", "x": 9, "y": 1, "d": 17, "p": 2, "tau": 6113.945933835919}, {"type": "unload", "x": 1, "y": 1, "d": 17, "p": 3, "tau": 6133.945933835919}], "7": [{"type": "load", "x": 12, "y": 12, "d": 19, "p": 0, "tau": 20}, {"type": "move", "x": 12, "y": 11, "d": 19, "p": 1, "tau": 1038.2118382563194}, {"type": "unload", "x": 11, "y": 11, "d": 19, "p": 2, "tau": 1058.2118382563194}, {"type": "move", "x": 11, "y": 12, "d": null, "p": null, "tau": 2076.423676512639}, {"type": "move", "x": 12, "y": 9, "d": null, "p": null, "tau": 3420.334594732106}, {"type": "load", "x": 9, "y": 9, "d": 1, "p": 3, "tau": 3440.334594732106}, {"type": "move", "x": 9, "y": 5, "d": 1, "p": 4, "tau": 4305.793207106}, {"type": "swap", "x": 5, "y": 5, "d": 1, "p": 5, "tau": 4365.793207106}, {"type": "move", "x": 5, "y": 3, "d": 1, "p": 6, "tau": 5701.140118838301}, {"type": "unload", "x": 3, "y": 3, "d": 1, "p": 7, "tau": 5721.140118838301}], "8": [{"type": "move", "x": 8, "y": 4, "d": null, "p": null, "tau": 866.8167445770935}, {"type": "load", "x": 4, "y": 4, "d": 13, "p": 0, "tau": 886.8167445770935}, {"type": "move", "x": 4, "y": 8, "d": 13, "p": 1, "tau": 1753.633489154187}, {"type": "unload", "x": 8, "y": 8, "d": 13, "p": 2, "tau": 1773.633489154187}, {"type": "move", "x": 8, "y": 2, "d": null, "p": null, "tau": 2995.479839864399}, {"type": "load", "x": 2, "y": 2, "d": 4, "p": 0, "tau": 3015.479839864399}, {"type": "swap", "x": 2, "y": 2, "d": 4, "p": 1, "tau": 3075.479839864399}, {"type": "move", "x": 2, "y": 11, "d": 4, "p": 2, "tau": 4003.647819759731}, {"type": "swap", "x": 11, "y": 11, "d": 4, "p": 3, "tau": 4063.647819759731}, {"type": "move", "x": 11, "y": 7, "d": 4, "p": 4, "tau": 4933.302745372317}, {"type": "swap", "x": 7, "y": 7, "d": 4, "p": 5, "tau": 4993.302745372317}, {"type": "move", "x": 7, "y": 9, "d": 4, "p": 6, "tau": 5956.975179504302}, {"type": "unload", "x": 9, "y": 9, "d": 4, "p": 7, "tau": 5976.975179504302}], "9": [{"type": "load", "x": 20, "y": 20, "d": 22, "p": 0, "tau": 20}, {"type": "move", "x": 20, "y": 16, "d": 22, "p": 1, "tau": 736.7120227798299}, {"type": "unload", "x": 16, "y": 16, "d": 22, "p": 2, "tau": 756.7120227798299}, {"type": "move", "x": 16, "y": 20, "d": null, "p": null, "tau": 1473.4240455596598}, {"type": "load", "x": 20, "y": 20, "d": 6, "p": 0, "tau": 1493.4240455596598}, {"type": "swap", "x": 20, "y": 20, "d": 6, "p": 1, "tau": 1553.4240455596598}, {"type": "move", "x": 20, "y": 6, "d": 6, "p": 2, "tau": 2647.903838815645}, {"type": "swap", "x": 6, "y": 6, "d": 6, "p": 3, "tau": 2707.903838815645}, {"type": "move", "x": 6, "y": 5, "d": 6, "p": 4, "tau": 3488.6932880198137}, {"type": "swap", "x": 5, "y": 5, "d": 6, "p": 5, "tau": 3548.6932880198137}, {"type": "move", "x": 5, "y": 7, "d": 6, "p": 6, "tau": 4381.960430037636}, {"type": "swap", "x": 7, "y": 7, "d": 6, "p": 7, "tau": 4441.960430037636}, {"type": "move", "x": 7, "y": 12, "d": 6, "p": 8, "tau": 5287.228045926566}, {"type": "swap", "x": 12, "y": 12, "d": 6, "p": 9, "tau": 5347.228045926566}, {"type": "move", "x": 12, "y": 13, "d": 6, "p": 10, "tau": 6175.711863204554}, {"type": "unload", "x": 13, "y": 13, "d": 6, "p": 11, "tau": 6195.711863204554}], "10": [{"type": "load", "x": 12, "y": 12, "d": 3, "p": 0, "tau": 20}, {"type": "move", "x": 12, "y": 9, "d": 3, "p": 1, "tau": 1363.9109182194668}, {"type": "unload", "x": 9, "y": 9, "d": 3, "p": 2, "tau": 1383.9109182194668}, {"type": "move", "x": 9, "y": 5, "d": null, "p": null, "tau": 2249.369530593361}, {"type": "load", "x": 5, "y": 5, "d": 11, "p": 0, "tau": 2269.369530593361}, {"type": "swap", "x": 5, "y": 5, "d": 11, "p": 1, "tau": 2329.369530593361}, {"type": "move", "x": 5, "y": 6, "d": 11, "p": 2, "tau": 3110.1589797975294}, {"type": "unload", "x": 6, "y": 6, "d": 11, "p": 3, "tau": 3130.1589797975294}, {"type": "load", "x": 6, "y": 6, "d": 12, "p": 0, "tau": 3150.1589797975294}, {"type": "move", "x": 6, "y": 14, "d": 12, "p": 1, "tau": 4876.420637020919}, {"type": "unload", "x": 14, "y": 14, "d": 12, "p": 2, "tau": 4896.420637020919}], "11": [{"type": "move", "x": 17, "y": 9, "d": null, "p": null, "tau": 796.0046208112886}, {"type": "load", "x": 9, "y": 9, "d": 9, "p": 0, "tau": 816.0046208112886}, {"type": "move", "x": 9, "y": 17, "d": 9, "p": 1, "tau": 1612.0092416225773}, {"type": "unload", "x": 17, "y": 17, "d": 9, "p": 2, "tau": 1632.0092416225773}, {"type": "move", "x": 17, "y": 13, "d": null, "p": null, "tau": 2710.488737902338}, {"type": "load", "x": 13, "y": 13, "d": 14, "p": 0, "tau": 2730.488737902338}, {"type": "move", "x": 13, "y": 2, "d": 14, "p": 1, "tau": 5498.203231256626}, {"type": "unload", "x": 2, "y": 2, "d": 14, "p": 2, "tau": 5518.203231256626}], "12": [{"type": "load", "x": 11, "y": 11, "d": 25, "p": 0, "tau": 20}, {"type": "move", "x": 11, "y": 1, "d": 25, "p": 1, "tau": 1706.0087333427216}, {"type": "unload", "x": 1, "y": 1, "d": 25, "p": 2, "tau": 1726.0087333427216}, {"type": "load", "x": 1, "y": 1, "d": 20, "p": 0, "tau": 1746.0087333427216}, {"type": "swap", "x": 1, "y": 1, "d": 20, "p": 1, "tau": 1806.0087333427216}, {"type": "move", "x": 1, "y": 15, "d": 20, "p": 2, "tau": 5431.749387857659}, {"type": "unload", "x": 15, "y": 15, "d": 20, "p": 3, "tau": 5451.749387857659}]}