{"1": [{"type": "move", "x": 17, "y": 5, "d": null, "p": null, "tau": 1960.8170253724948}, {"type": "load", "x": 5, "y": 5, "d": 23, "p": 0, "tau": 1980.8170253724948}, {"type": "move", "x": 5, "y": 14, "d": 23, "p": 1, "tau": 3624.5008350226167}, {"type": "unload", "x": 14, "y": 14, "d": 23, "p": 2, "tau": 3644.5008350226167}, {"type": "load", "x": 14, "y": 14, "d": 24, "p": 0, "tau": 3664.5008350226167}, {"type": "swap", "x": 14, "y": 14, "d": 24, "p": 1, "tau": 3724.5008350226167}, {"type": "move", "x": 14, "y": 1, "d": 24, "p": 2, "tau": 4495.536653293508}, {"type": "swap", "x": 1, "y": 1, "d": 24, "p": 3, "tau": 4555.536653293508}, {"type": "move", "x": 1, "y": 20, "d": 24, "p": 4, "tau": 5318.563369061766}, {"type": "unload", "x": 20, "y": 20, "d": 24, "p": 5, "tau": 5338.563369061766}], "2": [{"type": "load", "x": 8, "y": 8, "d": 17, "p": 0, "tau": 20}, {"type": "move", "x": 8, "y": 13, "d": 17, "p": 1, "tau": 996.9737580854211}, {"type": "unload", "x": 13, "y": 13, "d": 17, "p": 2, "tau": 1016.9737580854211}, {"type": "move", "x": 13, "y": 19, "d": null, "p": null, "tau": 2857.2272967599833}, {"type": "load", "x": 19, "y": 19, "d": 1, "p": 0, "tau": 2877.2272967599833}, {"type": "swap", "x": 19, "y": 19, "d": 1, "p": 1, "tau": 2937.2272967599833}, {"type": "move", "x": 19, "y": 8, "d": 1, "p": 2, "tau": 3901.545235110814}, {"type": "swap", "x": 8, "y": 8, "d": 1, "p": 3, "tau": 3961.545235110814}, {"type": "move", "x": 8, "y": 12, "d": 1, "p": 4, "tau": 5319.1975788369955}, {"type": "unload", "x": 12, "y": 12, "d": 1, "p": 5, "tau": 5339.1975788369955}], "3": [{"type": "move", "x": 5, "y": 20, "d": null, "p": null, "tau": 1516.3225186826041}, {"type": "load", "x": 20, "y": 20, "d": 16, "p": 3, "tau": 1815.1150178324551}, {"type": "move", "x": 20, "y": 16, "d": 16, "p": 4, "tau": 5015.830814692982}, {"type": "unload", "x": 16, "y": 16, "d": 16, "p": 5, "tau": 5035.830814692982}], "4": [{"type": "load", "x": 11, "y": 11, "d": 16, "p": 0, "tau": 20}, {"type": "move", "x": 11, "y": 20, "d": 16, "p": 1, "tau": 1775.1150178324551}, {"type": "unload", "x": 20, "y": 20, "d": 16, "p": 2, "tau": 1795.1150178324551}, {"type": "move", "x": 20, "y": 15, "d": null, "p": null, "tau": 3905.771885232882}, {"type": "load", "x": 15, "y": 15, "d": 21, "p": 0, "tau": 3925.771885232882}, {"type": "swap", "x": 15, "y": 15, "d": 21, "p": 1, "tau": 3985.771885232882}, {"type": "move", "x": 15, "y": 6, "d": 21, "p": 2, "tau": 5158.1070999280655}, {"type": "unload", "x": 6, "y": 6, "d": 21, "p": 3, "tau": 5178.1070999280655}], "5": [{"type": "load", "x": 17, "y": 17, "d": 6, "p": 0, "tau": 20}, {"type": "move", "x": 17, "y": 20, "d": 6, "p": 1, "tau": 2255.843798445345}, {"type": "unload", "x": 20, "y": 20, "d": 6, "p": 2, "tau": 2275.843798445345}, {"type": "load", "x": 20, "y": 20, "d": 9, "p": 0, "tau": 2295.843798445345}, {"type": "swap", "x": 20, "y": 20, "d": 9, "p": 1, "tau": 2355.843798445345}, {"type": "move", "x": 20, "y": 12, "d": 9, "p": 2, "tau": 5145.38229131091}, {"type": "unload", "x": 12, "y": 12, "d": 9, "p": 3, "tau": 5165.38229131091}], "6": [{"type": "move", "x": 9, "y": 17, "d": null, "p": null, "tau": 950.6991798138864}, {"type": "load", "x": 17, "y": 17, "d": 25, "p": 0, "tau": 970.6991798138864}, {"type": "move", "x": 17, "y": 11, "d": 25, "p": 1, "tau": 1705.3318863021834}, {"type": "unload", "x": 11, "y": 11, "d": 25, "p": 2, "tau": 1725.3318863021834}, {"type": "move", "x": 11, "y": 20, "d": null, "p": null, "tau": 3480.4469041346383}, {"type": "load", "x": 20, "y": 20, "d": 6, "p": 3, "tau": 3500.4469041346383}, {"type": "swap", "x": 20, "y": 20, "d": 6, "p": 4, "tau": 3560.4469041346383}, {"type": "move", "x": 20, "y": 2, "d": 6, "p": 5, "tau": 4663.179133575228}, {"type": "unload", "x": 2, "y": 2, "d": 6, "p": 6, "tau": 4683.179133575228}], "7": [{"type": "move", "x": 2, "y": 15, "d": null, "p": null, "tau": 1039.7554485588255}, {"type": "load", "x": 15, "y": 15, "d": 19, "p": 3, "tau": 1099.7554485588255}, {"type": "move", "x": 15, "y": 10, "d": 19, "p": 4, "tau": 2245.170395039244}, {"type": "unload", "x": 10, "y": 10, "d": 19, "p": 5, "tau": 2265.170395039244}, {"type": "move", "x": 10, "y": 19, "d": null, "p": null, "tau": 3022.525800380297}, {"type": "move", "x": 19, "y": 8, "d": null, "p": null, "tau": 3986.8437387311274}, {"type": "load", "x": 8, "y": 8, "d": 4, "p": 9, "tau": 4006.8437387311274}, {"type": "swap", "x": 8, "y": 8, "d": 4, "p": 10, "tau": 4066.8437387311274}, {"type": "move", "x": 8, "y": 13, "d": 4, "p": 11, "tau": 5043.817496816549}, {"type": "unload", "x": 13, "y": 13, "d": 4, "p": 12, "tau": 5063.817496816549}], "8": [{"type": "move", "x": 9, "y": 4, "d": null, "p": null, "tau": 906.6878498700695}, {"type": "load", "x": 4, "y": 4, "d": 14, "p": 0, "tau": 926.6878498700695}, {"type": "move", "x": 4, "y": 17, "d": 14, "p": 1, "tau": 1858.930941221457}, {"type": "unload", "x": 17, "y": 17, "d": 14, "p": 2, "tau": 1878.930941221457}], "9": [{"type": "move", "x": 19, "y": 10, "d": null, "p": null, "tau": 757.3554053410531}, {"type": "load", "x": 10, "y": 10, "d": 15, "p": 0, "tau": 777.3554053410531}, {"type": "move", "x": 10, "y": 6, "d": 15, "p": 1, "tau": 1832.4155822645735}, {"type": "unload", "x": 6, "y": 6, "d": 15, "p": 2, "tau": 1852.4155822645735}, {"type": "move", "x": 6, "y": 15, "d": null, "p": null, "tau": 3024.7507969597573}, {"type": "load", "x": 15, "y": 15, "d": 8, "p": 0, "tau": 3044.7507969597573}, {"type": "swap", "x": 15, "y": 15, "d": 8, "p": 1, "tau": 3104.7507969597573}, {"type": "move", "x": 15, "y": 20, "d": 8, "p": 2, "tau": 5215.407664360184}, {"type": "unload", "x": 20, "y": 20, "d": 8, "p": 3, "tau": 5235.407664360184}], "10": [{"type": "load", "x": 19, "y": 19, "d": 12, "p": 0, "tau": 20}, {"type": "move", "x": 19, "y": 8, "d": 12, "p": 1, "tau": 984.3179383508304}, {"type": "swap", "x": 8, "y": 8, "d": 12, "p": 2, "tau": 1044.3179383508304}, {"type": "move", "x": 8, "y": 7, "d": 12, "p": 3, "tau": 1831.3308157024628}, {"type": "swap", "x": 7, "y": 7, "d": 12, "p": 4, "tau": 1891.3308157024628}, {"type": "move", "x": 7, "y": 9, "d": 12, "p": 5, "tau": 3160.4646823840394}, {"type": "swap", "x": 9, "y": 9, "d": 12, "p": 6, "tau": 3220.4646823840394}, {"type": "move", "x": 9, "y": 17, "d": 12, "p": 7, "tau": 4171.1638621979255}, {"type": "unload", "x": 17, "y": 17, "d": 12, "p": 8, "tau": 4191.1638621979255}], "11": [{"type": "move", "x": 7, "y": 12, "d": null, "p": null, "tau": 888.9585001945688}, {"type": "load", "x": 12, "y": 12, "d": 5, "p": 0, "tau": 908.9585001945688}, {"type": "move", "x": 12, "y": 4, "d": 5, "p": 1, "tau": 2392.5304414798265}, {"type": "unload", "x": 4, "y": 4, "d": 5, "p": 2, "tau": 2412.5304414798265}], "12": [{"type": "move", "x": 2, "y": 20, "d": null, "p": null, "tau": 1102.732229440589}, {"type": "load", "x": 20, "y": 20, "d": 10, "p": 0, "tau": 1122.732229440589}, {"type": "swap", "x": 20, "y": 20, "d": 10, "p": 1, "tau": 1182.732229440589}, {"type": "move", "x": 20, "y": 4, "d": 10, "p": 2, "tau": 2659.572014521845}, {"type": "swap", "x": 4, "y": 4, "d": 10, "p": 3, "tau": 2719.572014521845}, {"type": "move", "x": 4, "y": 9, "d": 10, "p": 4, "tau": 3626.2598643919146}, {"type": "swap", "x": 9, "y": 9, "d": 10, "p": 5, "tau": 3686.2598643919146}, {"type": "move", "x": 9, "y": 18, "d": 10, "p": 6, "tau": 5166.517957351195}, {"type": "unload", "x": 18, "y": 18, "d": 10, "p": 7, "tau": 5186.517957351195}], "13": [{"type": "move", "x": 7, "y": 6, "d": null, "p": null, "tau": 730.6665277031765}, {"type": "move", "x": 6, "y": 1, "d": null, "p": null, "tau": 2868.42970205273}, {"type": "load", "x": 1, "y": 1, "d": 7, "p": 0, "tau": 2888.42970205273}, {"type": "swap", "x": 1, "y": 1, "d": 7, "p": 1, "tau": 2948.42970205273}, {"type": "move", "x": 1, "y": 11, "d": 7, "p": 2, "tau": 5452.749502311895}, {"type": "unload", "x": 11, "y": 11, "d": 7, "p": 3, "tau": 5472.749502311895}], "14": [{"type": "move", "x": 17, "y": 16, "d": null, "p": null, "tau": 1505.5079726841493}, {"type": "load", "x": 16, "y": 16, "d": 13, "p": 0, "tau": 1525.5079726841493}, {"type": "move", "x": 16, "y": 11, "d": 13, "p": 1, "tau": 3727.386774108828}, {"type": "unload", "x": 11, "y": 11, "d": 13, "p": 2, "tau": 3747.386774108828}], "15": [{"type": "load", "x": 2, "y": 2, "d": 19, "p": 0, "tau": 20}, {"type": "move", "x": 2, "y": 15, "d": 19, "p": 1, "tau": 1059.7554485588255}, {"type": "unload", "x": 15, "y": 15, "d": 19, "p": 2, "tau": 1079.7554485588255}, {"type": "load", "x": 15, "y": 15, "d": 2, "p": 0, "tau": 1099.7554485588255}, {"type": "swap", "x": 15, "y": 15, "d": 2, "p": 1, "tau": 1159.7554485588255}, {"type": "move", "x": 15, "y": 2, "d": 2, "p": 2, "tau": 2199.510897117651}, {"type": "unload", "x": 2, "y": 2, "d": 2, "p": 3, "tau": 2219.510897117651}, {"type": "move", "x": 2, "y": 6, "d": null, "p": null, "tau": 3414.337052460077}, {"type": "load", "x": 6, "y": 6, "d": 20, "p": 0, "tau": 3434.337052460077}, {"type": "swap", "x": 6, "y": 6, "d": 20, "p": 1, "tau": 3494.337052460077}, {"type": "move", "x": 6, "y": 7, "d": 20, "p": 2, "tau": 4225.003580163253}, {"type": "swap", "x": 7, "y": 7, "d": 20, "p": 3, "tau": 4285.003580163253}, {"type": "move", "x": 7, "y": 12, "d": 20, "p": 4, "tau": 5173.962080357822}, {"type": "unload", "x": 12, "y": 12, "d": 20, "p": 5, "tau": 5193.962080357822}], "16": [{"type": "move", "x": 13, "y": 19, "d": null, "p": null, "tau": 1840.2535386745624}, {"type": "load", "x": 19, "y": 19, "d": 22, "p": 0, "tau": 1860.2535386745624}, {"type": "move", "x": 19, "y": 20, "d": 22, "p": 1, "tau": 5401.691369290157}, {"type": "unload", "x": 20, "y": 20, "d": 22, "p": 2, "tau": 5421.691369290157}], "17": [{"type": "load", "x": 16, "y": 16, "d": 11, "p": 0, "tau": 20}, {"type": "move", "x": 16, "y": 9, "d": 11, "p": 1, "tau": 868.0897136395305}, {"type": "unload", "x": 9, "y": 9, "d": 11, "p": 2, "tau": 888.0897136395305}, {"type": "load", "x": 9, "y": 9, "d": 18, "p": 0, "tau": 908.0897136395305}, {"type": "move", "x": 9, "y": 12, "d": 18, "p": 1, "tau": 1630.5292872109248}, {"type": "swap", "x": 12, "y": 12, "d": 18, "p": 2, "tau": 1690.5292872109248}, {"type": "move", "x": 12, "y": 7, "d": 18, "p": 3, "tau": 2579.4877874054937}, {"type": "unload", "x": 7, "y": 7, "d": 18, "p": 4, "tau": 2599.4877874054937}], "18": [{"type": "load", "x": 20, "y": 20, "d": 4, "p": 0, "tau": 20}, {"type": "move", "x": 20, "y": 3, "d": 4, "p": 1, "tau": 778.7040666949546}, {"type": "swap", "x": 3, "y": 3, "d": 4, "p": 2, "tau": 838.7040666949546}, {"type": "move", "x": 3, "y": 5, "d": 4, "p": 3, "tau": 1815.1454678098444}, {"type": "swap", "x": 5, "y": 5, "d": 4, "p": 4, "tau": 1875.1454678098444}, {"type": "move", "x": 5, "y": 7, "d": 4, "p": 5, "tau": 2793.4437055458875}, {"type": "swap", "x": 7, "y": 7, "d": 4, "p": 6, "tau": 2853.4437055458875}, {"type": "move", "x": 7, "y": 8, "d": 4, "p": 7, "tau": 3640.45658289752}, {"type": "unload", "x": 8, "y": 8, "d": 4, "p": 8, "tau": 3660.45658289752}, {"type": "load", "x": 8, "y": 8, "d": 3, "p": 0, "tau": 3680.45658289752}, {"type": "swap", "x": 8, "y": 8, "d": 3, "p": 1, "tau": 3740.45658289752}, {"type": "move", "x": 8, "y": 5, "d": 3, "p": 2, "tau": 5333.270842233853}, {"type": "unload", "x": 5, "y": 5, "d": 3, "p": 3, "tau": 5353.270842233853}]}