{"1": [{"type": "move", "x": 13, "y": 11, "d": null, "p": null, "tau": 718.8566050657546}, {"type": "load", "x": 11, "y": 11, "d": 11, "p": 0, "tau": 738.8566050657546}, {"type": "move", "x": 11, "y": 8, "d": 11, "p": 1, "tau": 1469.8550441467967}, {"type": "swap", "x": 8, "y": 8, "d": 11, "p": 2, "tau": 1529.8550441467967}, {"type": "move", "x": 8, "y": 3, "d": 11, "p": 3, "tau": 2432.973582465439}, {"type": "swap", "x": 3, "y": 3, "d": 11, "p": 4, "tau": 2492.973582465439}, {"type": "move", "x": 3, "y": 1, "d": 11, "p": 5, "tau": 3392.6068202513543}, {"type": "unload", "x": 1, "y": 1, "d": 11, "p": 6, "tau": 3412.6068202513543}, {"type": "load", "x": 1, "y": 1, "d": 6, "p": 0, "tau": 3432.6068202513543}, {"type": "swap", "x": 1, "y": 1, "d": 6, "p": 1, "tau": 3492.6068202513543}, {"type": "move", "x": 1, "y": 7, "d": 6, "p": 2, "tau": 5964.825222114023}, {"type": "unload", "x": 7, "y": 7, "d": 6, "p": 3, "tau": 5984.825222114023}], "2": [{"type": "load", "x": 14, "y": 14, "d": 15, "p": 3, "tau": 836.4456901786406}, {"type": "move", "x": 14, "y": 10, "d": 15, "p": 4, "tau": 1952.3701138549764}, {"type": "unload", "x": 10, "y": 10, "d": 15, "p": 5, "tau": 1972.3701138549764}, {"type": "load", "x": 10, "y": 10, "d": 10, "p": 0, "tau": 1992.3701138549764}, {"type": "swap", "x": 10, "y": 10, "d": 10, "p": 1, "tau": 2052.3701138549764}, {"type": "move", "x": 10, "y": 11, "d": 10, "p": 2, "tau": 4147.110537799572}, {"type": "unload", "x": 11, "y": 11, "d": 10, "p": 3, "tau": 4167.110537799572}, {"type": "move", "x": 11, "y": 14, "d": null, "p": null, "tau": 5168.383657655084}, {"type": "load", "x": 14, "y": 14, "d": 5, "p": 0, "tau": 5188.383657655084}, {"type": "swap", "x": 14, "y": 14, "d": 5, "p": 1, "tau": 5248.383657655084}, {"type": "move", "x": 14, "y": 2, "d": 5, "p": 2, "tau": 7563.456203712056}, {"type": "unload", "x": 2, "y": 2, "d": 5, "p": 3, "tau": 7583.456203712056}], "3": [{"type": "load", "x": 5, "y": 5, "d": 18, "p": 0, "tau": 20}, {"type": "move", "x": 5, "y": 2, "d": 18, "p": 1, "tau": 756.8260920876444}, {"type": "swap", "x": 2, "y": 2, "d": 18, "p": 2, "tau": 816.8260920876444}, {"type": "move", "x": 2, "y": 3, "d": 18, "p": 3, "tau": 2308.8986751257803}, {"type": "unload", "x": 3, "y": 3, "d": 18, "p": 4, "tau": 2328.8986751257803}, {"type": "move", "x": 3, "y": 10, "d": null, "p": null, "tau": 4055.491111104987}, {"type": "swap", "x": 10, "y": 10, "d": null, "p": null, "tau": 4115.491111104987}, {"type": "move", "x": 10, "y": 3, "d": null, "p": null, "tau": 5842.083547084193}, {"type": "load", "x": 3, "y": 3, "d": 13, "p": 5, "tau": 5862.083547084193}, {"type": "swap", "x": 3, "y": 3, "d": 13, "p": 6, "tau": 5922.083547084193}, {"type": "move", "x": 3, "y": 19, "d": 13, "p": 7, "tau": 7333.1105534451635}, {"type": "unload", "x": 19, "y": 19, "d": 13, "p": 8, "tau": 7353.1105534451635}], "4": [{"type": "move", "x": 14, "y": 17, "d": null, "p": null, "tau": 1073.6610588371248}, {"type": "load", "x": 17, "y": 17, "d": 20, "p": 0, "tau": 1093.6610588371248}, {"type": "move", "x": 17, "y": 16, "d": 20, "p": 1, "tau": 1944.3978224751077}, {"type": "unload", "x": 16, "y": 16, "d": 20, "p": 2, "tau": 1964.3978224751077}, {"type": "load", "x": 16, "y": 16, "d": 1, "p": 0, "tau": 1984.3978224751077}, {"type": "swap", "x": 16, "y": 16, "d": 1, "p": 1, "tau": 2044.3978224751077}, {"type": "move", "x": 16, "y": 14, "d": 1, "p": 2, "tau": 3546.31009034594}, {"type": "unload", "x": 14, "y": 14, "d": 1, "p": 3, "tau": 3566.31009034594}, {"type": "swap", "x": 14, "y": 14, "d": null, "p": null, "tau": 3626.31009034594}, {"type": "move", "x": 14, "y": 10, "d": null, "p": null, "tau": 4742.234514022275}, {"type": "load", "x": 10, "y": 10, "d": 16, "p": 0, "tau": 4762.234514022275}, {"type": "move", "x": 10, "y": 1, "d": 16, "p": 1, "tau": 6917.891476642686}, {"type": "unload", "x": 1, "y": 1, "d": 16, "p": 2, "tau": 6937.891476642686}], "5": [{"type": "load", "x": 20, "y": 20, "d": 7, "p": 0, "tau": 20}, {"type": "move", "x": 20, "y": 18, "d": 7, "p": 1, "tau": 1349.778810478045}, {"type": "unload", "x": 18, "y": 18, "d": 7, "p": 2, "tau": 1369.778810478045}, {"type": "move", "x": 18, "y": 11, "d": null, "p": null, "tau": 3229.8122089857898}, {"type": "load", "x": 11, "y": 11, "d": 13, "p": 0, "tau": 3249.8122089857898}, {"type": "move", "x": 11, "y": 8, "d": 13, "p": 1, "tau": 3980.810648066832}, {"type": "swap", "x": 8, "y": 8, "d": 13, "p": 2, "tau": 4040.810648066832}, {"type": "move", "x": 8, "y": 3, "d": 13, "p": 3, "tau": 4943.929186385474}, {"type": "unload", "x": 3, "y": 3, "d": 13, "p": 4, "tau": 4963.929186385474}, {"type": "load", "x": 3, "y": 3, "d": 9, "p": 0, "tau": 4983.929186385474}, {"type": "swap", "x": 3, "y": 3, "d": 9, "p": 1, "tau": 5043.929186385474}, {"type": "move", "x": 3, "y": 6, "d": 9, "p": 2, "tau": 6020.257659966069}, {"type": "unload", "x": 6, "y": 6, "d": 9, "p": 3, "tau": 6040.257659966069}, {"type": "load", "x": 6, "y": 6, "d": 1, "p": 8, "tau": 6683.12518128828}, {"type": "move", "x": 6, "y": 18, "d": 1, "p": 9, "tau": 7527.96353636505}, {"type": "unload", "x": 18, "y": 18, "d": 1, "p": 10, "tau": 7547.96353636505}], "6": [{"type": "move", "x": 2, "y": 3, "d": null, "p": null, "tau": 1492.072583038136}, {"type": "move", "x": 3, "y": 8, "d": null, "p": null, "tau": 2395.1911213567782}, {"type": "load", "x": 8, "y": 8, "d": 14, "p": 0, "tau": 2415.1911213567782}, {"type": "move", "x": 8, "y": 13, "d": 14, "p": 1, "tau": 3776.1975941040237}, {"type": "unload", "x": 13, "y": 13, "d": 14, "p": 2, "tau": 3796.1975941040237}, {"type": "load", "x": 13, "y": 13, "d": 12, "p": 0, "tau": 3816.1975941040237}, {"type": "swap", "x": 13, "y": 13, "d": 12, "p": 1, "tau": 3876.1975941040237}, {"type": "move", "x": 13, "y": 6, "d": 12, "p": 2, "tau": 5149.1732379154455}, {"type": "swap", "x": 6, "y": 6, "d": 12, "p": 3, "tau": 5209.1732379154455}, {"type": "move", "x": 6, "y": 9, "d": 12, "p": 4, "tau": 6480.483551374842}, {"type": "swap", "x": 9, "y": 9, "d": 12, "p": 5, "tau": 6540.483551374842}, {"type": "move", "x": 9, "y": 19, "d": 12, "p": 6, "tau": 7264.685103989422}, {"type": "unload", "x": 19, "y": 19, "d": 12, "p": 7, "tau": 7284.685103989422}], "7": [{"type": "move", "x": 18, "y": 20, "d": null, "p": null, "tau": 1329.778810478045}, {"type": "load", "x": 20, "y": 20, "d": 3, "p": 0, "tau": 1349.778810478045}, {"type": "move", "x": 20, "y": 19, "d": 3, "p": 1, "tau": 2348.4154340802916}, {"type": "swap", "x": 19, "y": 19, "d": 3, "p": 2, "tau": 2408.4154340802916}, {"type": "move", "x": 19, "y": 1, "d": 3, "p": 3, "tau": 3151.2879219236193}, {"type": "unload", "x": 1, "y": 1, "d": 3, "p": 4, "tau": 3171.2879219236193}, {"type": "move", "x": 1, "y": 14, "d": null, "p": null, "tau": 5406.839030169407}, {"type": "load", "x": 14, "y": 14, "d": 8, "p": 4, "tau": 5426.839030169407}, {"type": "swap", "x": 14, "y": 14, "d": 8, "p": 5, "tau": 5486.839030169407}, {"type": "move", "x": 14, "y": 11, "d": 8, "p": 6, "tau": 6488.112150024919}, {"type": "move", "x": 11, "y": 7, "d": 8, "p": 7, "tau": 7571.13644018042}, {"type": "unload", "x": 7, "y": 7, "d": 8, "p": 8, "tau": 7591.13644018042}], "8": [{"type": "load", "x": 15, "y": 15, "d": 15, "p": 0, "tau": 20}, {"type": "move", "x": 15, "y": 14, "d": 15, "p": 1, "tau": 796.4456901786406}, {"type": "unload", "x": 14, "y": 14, "d": 15, "p": 2, "tau": 816.4456901786406}, {"type": "move", "x": 14, "y": 8, "d": null, "p": null, "tau": 1562.1128411506252}, {"type": "move", "x": 8, "y": 17, "d": null, "p": null, "tau": 3368.493720834529}, {"type": "load", "x": 17, "y": 17, "d": 8, "p": 0, "tau": 3388.493720834529}, {"type": "swap", "x": 17, "y": 17, "d": 8, "p": 1, "tau": 3448.493720834529}, {"type": "move", "x": 17, "y": 14, "d": 8, "p": 2, "tau": 4522.154779671654}, {"type": "unload", "x": 14, "y": 14, "d": 8, "p": 3, "tau": 4542.154779671654}, {"type": "load", "x": 14, "y": 14, "d": 2, "p": 0, "tau": 4562.154779671654}, {"type": "move", "x": 14, "y": 8, "d": 2, "p": 1, "tau": 5307.821930643639}, {"type": "swap", "x": 8, "y": 8, "d": 2, "p": 2, "tau": 5367.821930643639}, {"type": "move", "x": 8, "y": 6, "d": 2, "p": 3, "tau": 6202.623681142781}, {"type": "swap", "x": 6, "y": 6, "d": 2, "p": 4, "tau": 6262.623681142781}, {"type": "move", "x": 6, "y": 18, "d": 2, "p": 5, "tau": 7107.46203621955}, {"type": "unload", "x": 18, "y": 18, "d": 2, "p": 6, "tau": 7127.46203621955}], "9": [{"type": "move", "x": 19, "y": 9, "d": null, "p": null, "tau": 724.20155261458}, {"type": "load", "x": 9, "y": 9, "d": 17, "p": 0, "tau": 744.20155261458}, {"type": "move", "x": 9, "y": 2, "d": 17, "p": 1, "tau": 2702.805605669648}, {"type": "unload", "x": 2, "y": 2, "d": 17, "p": 2, "tau": 2722.805605669648}, {"type": "move", "x": 2, "y": 3, "d": null, "p": null, "tau": 4214.878188707784}, {"type": "load", "x": 3, "y": 3, "d": 19, "p": 0, "tau": 4234.878188707784}, {"type": "swap", "x": 3, "y": 3, "d": 19, "p": 1, "tau": 4294.878188707784}, {"type": "move", "x": 3, "y": 6, "d": 19, "p": 2, "tau": 5271.2066622883785}, {"type": "swap", "x": 6, "y": 6, "d": 19, "p": 3, "tau": 5331.2066622883785}, {"type": "move", "x": 6, "y": 18, "d": 19, "p": 4, "tau": 6176.045017365148}, {"type": "unload", "x": 18, "y": 18, "d": 19, "p": 5, "tau": 6196.045017365148}], "10": [{"type": "load", "x": 17, "y": 17, "d": 4, "p": 0, "tau": 20}, {"type": "move", "x": 17, "y": 15, "d": 4, "p": 1, "tau": 1088.4985721130267}, {"type": "unload", "x": 15, "y": 15, "d": 4, "p": 2, "tau": 1108.4985721130267}, {"type": "swap", "x": 15, "y": 15, "d": null, "p": null, "tau": 1168.4985721130267}, {"type": "move", "x": 15, "y": 14, "d": null, "p": null, "tau": 1944.9442622916672}, {"type": "move", "x": 14, "y": 16, "d": null, "p": null, "tau": 3446.8565301624994}, {"type": "load", "x": 16, "y": 16, "d": 20, "p": 3, "tau": 3466.8565301624994}, {"type": "move", "x": 16, "y": 14, "d": 20, "p": 4, "tau": 4968.768798033332}, {"type": "unload", "x": 14, "y": 14, "d": 20, "p": 5, "tau": 4988.768798033332}, {"type": "load", "x": 14, "y": 14, "d": 1, "p": 4, "tau": 5008.768798033332}, {"type": "swap", "x": 14, "y": 14, "d": 1, "p": 5, "tau": 5068.768798033332}, {"type": "move", "x": 14, "y": 6, "d": 1, "p": 6, "tau": 6643.12518128828}, {"type": "unload", "x": 6, "y": 6, "d": 1, "p": 7, "tau": 6663.12518128828}, {"type": "load", "x": 6, "y": 6, "d": 9, "p": 4, "tau": 6683.12518128828}, {"type": "swap", "x": 6, "y": 6, "d": 9, "p": 5, "tau": 6743.12518128828}, {"type": "move", "x": 6, "y": 7, "d": 9, "p": 6, "tau": 7502.273211451298}, {"type": "unload", "x": 7, "y": 7, "d": 9, "p": 7, "tau": 7522.273211451298}]}